datahub_actions/__init__.py
datahub_actions/_version.py
datahub_actions/entrypoints.py
datahub_actions/action/__init__.py
datahub_actions/action/action.py
datahub_actions/action/action_registry.py
datahub_actions/action/action_stats.py
datahub_actions/api/__init__.py
datahub_actions/api/action_graph.py
datahub_actions/cli/__init__.py
datahub_actions/cli/actions.py
datahub_actions/event/__init__.py
datahub_actions/event/event.py
datahub_actions/event/event_envelope.py
datahub_actions/event/event_registry.py
datahub_actions/observability/__init__.py
datahub_actions/observability/kafka_lag_monitor.py
datahub_actions/pipeline/__init__.py
datahub_actions/pipeline/pipeline.py
datahub_actions/pipeline/pipeline_config.py
datahub_actions/pipeline/pipeline_context.py
datahub_actions/pipeline/pipeline_manager.py
datahub_actions/pipeline/pipeline_stats.py
datahub_actions/pipeline/pipeline_util.py
datahub_actions/plugin/__init__.py
datahub_actions/plugin/action/__init__.py
datahub_actions/plugin/action/mcl_utils.py
datahub_actions/plugin/action/stats_util.py
datahub_actions/plugin/action/execution/__init__.py
datahub_actions/plugin/action/execution/executor_action.py
datahub_actions/plugin/action/hello_world/__init__.py
datahub_actions/plugin/action/hello_world/hello_world.py
datahub_actions/plugin/action/metadata_change_sync/__init__.py
datahub_actions/plugin/action/metadata_change_sync/metadata_change_sync.py
datahub_actions/plugin/action/propagation/__init__.py
datahub_actions/plugin/action/propagation/propagation_utils.py
datahub_actions/plugin/action/propagation/docs/__init__.py
datahub_actions/plugin/action/propagation/docs/propagation_action.py
datahub_actions/plugin/action/slack/__init__.py
datahub_actions/plugin/action/slack/slack.py
datahub_actions/plugin/action/snowflake/__init__.py
datahub_actions/plugin/action/snowflake/snowflake_util.py
datahub_actions/plugin/action/snowflake/tag_propagator.py
datahub_actions/plugin/action/tag/__init__.py
acryl_datahub_actions-1.3.1.10.dist-info/METADATA
acryl_datahub_actions-1.3.1.10.dist-info/WHEEL
acryl_datahub_actions-1.3.1.10.dist-info/entry_points.txt
acryl_datahub_actions-1.3.1.10.dist-info/top_level.txt
acryl_datahub_actions-1.3.1.10.dist-info/RECORD
